[
  {
    "question": "What does the 'ls' command do in Linux?",
    "options": [
      "Displays system information",
      "Lists files and directories",
      "Moves files and directories",
      "Deletes files"
    ],
    "correctOption": "Lists files and directories",
    "points": 10
  },
  {
    "question": "What is the purpose of the 'chmod' command in Linux?",
    "options": [
      "Changes file ownership",
      "Lists file contents",
      "Changes file permissions",
      "Changes file content"
    ],
    "correctOption": "Changes file permissions",
    "points": 10
  },
  {
    "question": "What is the 'root' user in Linux?",
    "options": [
      "A regular user with limited access",
      "A file manager",
      "A system process",
      "The superuser with full system access"
    ],
    "correctOption": "The superuser with full system access",
    "points": 10
  },
  {
    "question": "Which command is used to change the current directory in Linux?",
    "options": ["cd", "ls", "pwd", "mv"],
    "correctOption": "cd",
    "points": 10
  },
  {
    "question": "What does the 'pwd' command do in Linux?",
    "options": [
      "Prints the last logged in user",
      "Prints the working directory",
      "Lists all files",
      "Changes the current directory"
    ],
    "correctOption": "Prints the working directory",
    "points": 10
  },
  {
    "question": "What is a Linux shell?",
    "options": [
      "A graphical user interface for interacting with the system",
      "A file management tool",
      "A command-line interface for interacting with the system",
      "A networking tool"
    ],
    "correctOption": "A command-line interface for interacting with the system",
    "points": 10
  },
  {
    "question": "Which command is used to display the contents of a file in Linux?",
    "options": ["ls", "touch", "rm", "cat"],
    "correctOption": "cat",
    "points": 10
  },
  {
    "question": "What does the 'cp' command do in Linux?",
    "options": [
      "Changes file permissions",
      "Deletes files",
      "Copies files and directories",
      "Moves files"
    ],
    "correctOption": "Copies files and directories",
    "points": 10
  },
  {
    "question": "How do you make a file executable in Linux?",
    "options": [
      "chmod 777 filename",
      "chmod +x filename",
      "mv filename /bin",
      "cp filename /usr"
    ],
    "correctOption": "chmod +x filename",
    "points": 10
  },
  {
    "question": "Which command is used to view the manual for a command in Linux?",
    "options": ["help", "info", "man", "guide"],
    "correctOption": "man",
    "points": 10
  },
  {
    "question": "What does the 'rm' command do in Linux?",
    "options": [
      "Renames files and directories",
      "Lists files",
      "Moves files",
      "Deletes files and directories"
    ],
    "correctOption": "Deletes files and directories",
    "points": 10
  },
  {
    "question": "What is a Linux distribution?",
    "options": [
      "A file manager for Linux",
      "A complete operating system built from the Linux kernel",
      "A type of Linux shell",
      "A Linux user group"
    ],
    "correctOption": "A complete operating system built from the Linux kernel",
    "points": 10
  },
  {
    "question": "What is the 'ls -l' command used for in Linux?",
    "options": [
      "Lists files in reverse order",
      "Changes the current directory",
      "Displays hidden files",
      "Displays detailed information about files and directories"
    ],
    "correctOption": "Displays detailed information about files and directories",
    "points": 10
  },
  {
    "question": "What is the purpose of the 'grep' command in Linux?",
    "options": [
      "Changes file permissions",
      "Lists files",
      "Searches for a pattern within files",
      "Copies files"
    ],
    "correctOption": "Searches for a pattern within files",
    "points": 10
  },
  {
    "question": "Which command is used to display the first 10 lines of a file in Linux?",
    "options": ["head", "tail", "cat", "more"],
    "correctOption": "head",
    "points": 10
  },
  {
    "question": "What does the 'df' command do in Linux?",
    "options": [
      "Displays disk space usage",
      "Displays file contents",
      "Displays memory usage",
      "Deletes files"
    ],
    "correctOption": "Displays disk space usage",
    "points": 10
  },
  {
    "question": "What is the purpose of the 'sudo' command in Linux?",
    "options": [
      "Changes file permissions",
      "Executes commands with superuser privileges",
      "Displays system information",
      "Lists files"
    ],
    "correctOption": "Executes commands with superuser privileges",
    "points": 10
  },
  {
    "question": "What does the 'top' command do in Linux?",
    "options": [
      "Displays system processes and resource usage",
      "Displays a file's contents",
      "Changes the system date and time",
      "Manages user permissions"
    ],
    "correctOption": "Displays system processes and resource usage",
    "points": 10
  },
  {
    "question": "What is the purpose of the 'ifconfig' command in Linux?",
    "options": [
      "Displays system information",
      "Manages disk partitions",
      "Displays network configuration information",
      "Changes file permissions"
    ],
    "correctOption": "Displays network configuration information",
    "points": 10
  },
  {
    "question": "What is the 'vi' editor in Linux?",
    "options": [
      "A file management tool",
      "A web server",
      "A system monitor",
      "A text editor"
    ],
    "correctOption": "A text editor",
    "points": 10
  },
  {
    "question": "Which command is used to create a new directory in Linux?",
    "options": ["mkdir", "rmdir", "touch", "cp"],
    "correctOption": "mkdir",
    "points": 10
  },
  {
    "question": "What is the 'ps' command used for in Linux?",
    "options": [
      "Displays file contents",
      "Changes file permissions",
      "Displays a list of running processes",
      "Displays disk space usage"
    ],
    "correctOption": "Displays a list of running processes",
    "points": 10
  },
  {
    "question": "Which of the following is a package manager for Linux?",
    "options": ["apt", "dpkg", "yum", "All of the above"],
    "correctOption": "All of the above",
    "points": 10
  },
  {
    "question": "What is the 'man' command used for in Linux?",
    "options": [
      "Creates a new file",
      "Displays the manual for a command",
      "Lists files in a directory",
      "Changes the current directory"
    ],
    "correctOption": "Displays the manual for a command",
    "points": 10
  },
  {
    "question": "What does the 'uptime' command do in Linux?",
    "options": [
      "Displays the system's uptime",
      "Updates the system",
      "Lists the files in a directory",
      "Changes file ownership"
    ],
    "correctOption": "Displays the system's uptime",
    "points": 10
  },
  {
    "question": "What is the purpose of the 'kill' command in Linux?",
    "options": [
      "Kills a user session",
      "Deletes files",
      "Terminates processes",
      "Clears the terminal screen"
    ],
    "correctOption": "Terminates processes",
    "points": 10
  },
  {
    "question": "What does the 'whoami' command do in Linux?",
    "options": [
      "Displays the current system date and time",
      "Displays a list of users",
      "Displays system processes",
      "Displays the current logged-in user"
    ],
    "correctOption": "Displays the current logged-in user",
    "points": 10
  },
  {
    "question": "What does the 'chmod' command do in Linux?",
    "options": [
      "Changes file permissions",
      "Changes file ownership",
      "Displays file contents",
      "Moves files"
    ],
    "correctOption": "Changes file permissions",
    "points": 10
  },
  {
    "question": "Which command is used to list all files, including hidden files, in a directory in Linux?",
    "options": ["ls -a", "ls -l", "list -a", "dir -all"],
    "correctOption": "ls -a",
    "points": 10
  },
  {
    "question": "What does the 'grep' command do in Linux?",
    "options": [
      "Displays system information",
      "Searches for patterns in a file",
      "Lists all running processes",
      "Displays file permissions"
    ],
    "correctOption": "Searches for patterns in a file",
    "points": 10
  }
]
